main.py
setup.py
piano_transcription.egg-info/PKG-INFO
piano_transcription.egg-info/SOURCES.txt
piano_transcription.egg-info/dependency_links.txt
piano_transcription.egg-info/requires.txt
piano_transcription.egg-info/top_level.txt