Metadata-Version: 2.1
Name: piano_transcription
Version: 912.6
Summary: x
Author: 214
Author-email: xxx@outlook.com
Requires-Dist: requests
